foliant/backends/aglio.py
foliantcontrib.aglio-1.0.0.dist-info/LICENSE
foliantcontrib.aglio-1.0.0.dist-info/METADATA
foliantcontrib.aglio-1.0.0.dist-info/WHEEL
foliantcontrib.aglio-1.0.0.dist-info/top_level.txt
foliantcontrib.aglio-1.0.0.dist-info/RECORD
